parseanno/__init__.py
parseanno/anno/__init__.py
parseanno/anno/base_anno.py
parseanno/anno/build.py
parseanno/anno/labelimg_anno.py
parseanno/anno/registry.py
parseanno/anno/tlt_anno.py
parseanno/anno/visdrone_anno.py
parseanno/anno/yolov5_anno.py
parseanno/config/__init__.py
parseanno/config/defaults.py
parseanno/engine/__init__.py
parseanno/engine/anno_processor.py
parseanno/engine/defaults.py
parseanno/tools/__init__.py
parseanno/tools/cli.py
parseanno/utils/__init__.py
parseanno/utils/logger.py
parseanno/utils/misc.py
parseanno/utils/parse_voc_xml.py
parseanno/utils/registry.py
parseanno/utils/utility.py
ParseAnno-0.1.9.dist-info/LICENSE
ParseAnno-0.1.9.dist-info/METADATA
ParseAnno-0.1.9.dist-info/WHEEL
ParseAnno-0.1.9.dist-info/entry_points.txt
ParseAnno-0.1.9.dist-info/top_level.txt
ParseAnno-0.1.9.dist-info/RECORD
