Metadata-Version: 2.1
Name: ParseAnno
Version: 0.1.9
Summary: Script for annotation data processing
Home-page: https://github.com/zjZSTU/ParseAnno
Author: zj
Author-email: wy163zhuj@163.com
License: UNKNOWN
Platform: UNKNOWN
Classifier: Programming Language :: Python :: 3
Classifier: Operating System :: OS Independent
Classifier: License :: OSI Approved :: Apache Software License
Requires-Python: >=3.6
Requires-Dist: yacs (>=0.1.7)
Requires-Dist: opencv-contrib-python (>=4.2.0)
Requires-Dist: numpy (>=1.17.2)
